LICENSE
MANIFEST.in
README.md
setup.py
projecto/__init__.py
projecto/seraqvai.py
projecto.egg-info/PKG-INFO
projecto.egg-info/SOURCES.txt
projecto.egg-info/dependency_links.txt
projecto.egg-info/not-zip-safe
projecto.egg-info/requires.txt
projecto.egg-info/top_level.txt